{"url": "https://oilprice.com/Latest-Energy-News/World-News/Oil-Prices-Jump-over-7-as-Iran-Ceasefire-Declared-Over.html", "fetched_at": "2026-07-08T17:14:55.363450+00:00", "status": "ok", "title": "Oil Prices Jump over 7% as Iran Ceasefire Declared \u2018Over\u2019 | OilPrice.com", "text": "Oil Prices Jump over 7% as Iran Ceasefire Declared \u2018Over\u2019\n\nAlex Kimani is a veteran finance writer, investor, engineer and researcher for Safehaven.com.\n\nOil prices surged over 7% to a two-week high on Wednesday after U.S. President Donald Trump declared that the interim ceasefire agreement with Iran is officially over and dismissed the recently signed memorandum of understanding as a \"waste of time.\" Brent crude for September delivery spiked 7.6% to trade at $79.76 per barrel at 10:40 am ET, while WTI crude for August delivery gained 7.2% to change hands at $75.4/bbl.\n\nIran attacked three commercial vessels transiting the Strait of Hormuz on Tuesday, prompting retaliatory attacks by the United States. The LNG tanker was struck on its port side, causing an engine room fire, while the Saudi-flagged supertanker suffered minor damage off the coast of Oman.\n\nIn response, U.S. Central Command (CENTCOM) conducted massive offensive airstrikes hitting more than 80 military targets inside Iran. According to CENTCOM, the operation utilized precision-guided and 5,000-pound deep penetrator munitions against multiple coastal areas, including Qeshm Island, Sirik, as well as the major port city of Bandar Abbas.\n\nThe Trump administration also revoked a temporary sanctions waiver that allowed Iran to sell oil and petrochemicals, cutting off a key revenue stream for Tehran. The Khatam al-Anbiya Central Headquarters in Tehran, on the other hand, announced the formal closure of the Strait of Hormuz, warning all international commercial shipping that any further attempts to transit the waterway would face direct military intervention. The scale of the assault--much larger than the previous reprisal actions-marks the effective collapse of the fragile interim ceasefire signed in June.\n\nFreight rates for tankers operating in the Gulf have surged as shipowners demand higher risk premiums, while refiners in Asia are scrambling to secure alternative cargoes from West Africa, the U.S., and Latin America in case Hormuz remains closed.\n\nGlobal Nuclear Power Capacity Set to Jump by 44% by 2036\n\nGlobal Nuclear Power Capacity Set to Jump by 44% by 2036\n\nAlex Kimani is a veteran finance writer, investor, engineer and researcher for Safehaven.com.\n\nOil Prices Plunge as U.S. and Iran Reach Deal to Reopen Strait of Hormuz\n\nOil Prices Rebound as U.S.-Iran Peace Talks Are Postponed\n\nING: Oil Prices Have Overshot To The Downside\n\nRussia\u2019s Oil Windfall Vanishes as Urals Crashes to $42 a Barrel\n\nIran Tightens Grip on Strait of Hormuz Tanker Traffic\n\nWhy a Supply Crunch From Iran Could Send Oil Back Below $40 a Barrel\n\nSaudi Arabia\u2019s Decided Who Its Future Superpower Partner Is, And It\u2019s Not the US\n\nSolar Is the Cheapest Power in History, But States Are Retreating From It\n\nGuyana\u2019s Oil Boom Gets a Major Boost From $100 Crude\n\nThe materials provided on this Web site are for informational and educational purposes only and are not intended to provide tax, legal, or investment advice.\n\nNothing contained on the Web site shall be considered a recommendation, solicitation, or offer to buy or sell a security to any person in any jurisdiction.\n\nMerchant of Record: A Media Solutions trading as Oilprice.com"}